{
   "Routes":[
      {
         "DownstreamPathTemplate":"/api/Authenticate",
         "DownstreamScheme":"http",
         "DownstreamHostAndPorts":[
            {
               "Host":"localhost",
               "Port":"7005"
            }
         ]
      },
      {
         "DownstreamPathTemplate":"/api/WeatherForecast",
         "DownstreamScheme":"http",
         "DownstreamHostAndPorts":[
            {
               "Host":"localhost",
               "Port":"7001"
            }
         ],
         "UpstreamPathTemplate":"/TestService",
         "UpstreamHttpMethod":[
            "GET"
         ],
         "AuthenticationOptions": {
            "AuthenticationProviderKey": "TestKey",
            "AllowedScopes": []
        }
      }
   ],
   "GlobalCOnfiguration":{
      "BaseUrl":"https://localhost:7000"
   }
}